kartinggrid/__init__.py
kartinggrid/hello.py
AOCs-1.dist-info/METADATA
AOCs-1.dist-info/WHEEL
AOCs-1.dist-info/top_level.txt
AOCs-1.dist-info/RECORD
