Metadata-Version: 2.1
Name: AOCs
Version: 1
Summary: to make the grid mans job easy
Home-page: https://github.com/ocalla22/GridSystem
Author: Andy OC
Author-email: andrew.ocallaghan@ucdconnect.ie
License: MIT
Platform: UNKNOWN
Classifier: License :: OSI Approved :: MIT License
Classifier: Programming Language :: Python :: 3.8
